pubmedmcp/__init__.py
pubmedmcp/__main__.py
iflow_mcp_grll_pubmedmcp-0.1.4.dist-info/METADATA
iflow_mcp_grll_pubmedmcp-0.1.4.dist-info/WHEEL
iflow_mcp_grll_pubmedmcp-0.1.4.dist-info/entry_points.txt
iflow_mcp_grll_pubmedmcp-0.1.4.dist-info/licenses/LICENSE
iflow_mcp_grll_pubmedmcp-0.1.4.dist-info/RECORD
